filemanips/__init__.py
filemanips/api.py
filemanips-1.0.3.dist-info/LICENSE
filemanips-1.0.3.dist-info/METADATA
filemanips-1.0.3.dist-info/WHEEL
filemanips-1.0.3.dist-info/top_level.txt
filemanips-1.0.3.dist-info/RECORD
