Metadata-Version: 2.1
Name: filemanips
Version: 1.0.3
Summary: File manipulation functions
Home-page: https://github.com/zmarffy/filemanips
Author: Zeke Marffy
Author-email: zmarffy@yahoo.com
License: MIT
Platform: UNKNOWN
Requires-Python: >=3.8
